downmixer/__init__.py
downmixer/library.py
downmixer/file_tools/__init__.py
downmixer/file_tools/convert.py
downmixer/file_tools/tag.py
downmixer/file_tools/utils.py
downmixer/log/__init__.py
downmixer/matching/__init__.py
downmixer/matching/utils.py
downmixer/processing/__init__.py
downmixer/providers/__init__.py
downmixer/providers/audio/__init__.py
downmixer/providers/audio/youtube_music.py
downmixer/providers/lyrics/__init__.py
downmixer/providers/lyrics/azlyrics.py
downmixer/spotify/__init__.py
downmixer/spotify/client.py
downmixer/spotify/utils.py
downmixer-0.0.1.dist-info/LICENSE
downmixer-0.0.1.dist-info/METADATA
downmixer-0.0.1.dist-info/WHEEL
downmixer-0.0.1.dist-info/entry_points.txt
downmixer-0.0.1.dist-info/top_level.txt
downmixer-0.0.1.dist-info/RECORD
