Metadata-Version: 2.1
Name: downmixer
Version: 0.0.1
Summary: Synchronize your Spotify library locally!
Author-email: Sam Rodrigues <sam.roliveira@proton.me>
Project-URL: Homepage, https://github.com/androidWG/downmixer
Project-URL: Documentation, https://androidwg.github.io/downmixer
Project-URL: Bug Tracker, https://github.com/androidWG/downmixer/issues
Classifier: Development Status :: 3 - Alpha
Classifier: Programming Language :: Python :: 3
Classifier: License :: OSI Approved :: GNU General Public License v3 (GPLv3)
Classifier: Operating System :: OS Independent
Classifier: Intended Audience :: Developers
Classifier: Typing :: Typed
Requires-Python: >=3.7
License-File: LICENSE
